RStockvn/__init__.py
RStockvn/cafef_test.py
RStockvn/ls_cafef.py
RStockvn/report_vnd.py
RStockvn/stockvn.py
RStockvn/update_package.py
RStockvn/user_agent.py
RStockvn/chrome_driver/__init__.py
RStockvn/chrome_driver/chromedriver_setup.py
RStockvn/chrome_driver/__pycache__/__init__.cpython-311.pyc
RStockvn/chrome_driver/__pycache__/chromedriver_setup.cpython-311.pyc
RStockvn/chrome_driver/macOS/LICENSE.chromedriver
RStockvn/chrome_driver/macOS/chromedriver
RStockvn/chrome_driver/macOS_arm/LICENSE.chromedriver
RStockvn/chrome_driver/macOS_arm/chromedriver
RStockvn/chrome_driver/windows/LICENSE.chromedriver
RStockvn/chrome_driver/windows/chromedriver.exe
RStockvn/data/__init__.py
RStockvn/data/donate_qr.jpg
RStockvn/data/ds_company.py
RStockvn/data/ds_ngành_đã_lọc.xlsx
RStockvn/data/dsnganh.xlsx
RStockvn/data/list_company.xlsx
rstockvn-5.0.dist-info/LICENSE
rstockvn-5.0.dist-info/METADATA
rstockvn-5.0.dist-info/WHEEL
rstockvn-5.0.dist-info/top_level.txt
rstockvn-5.0.dist-info/RECORD
