Metadata-Version: 2.2
Name: RStockvn
Version: 5.0
Summary: Report Finance of Companies in Vietnamese and macro data - Lấy báo cáo tài chính của các công ty ở Việt Nam và số liệu vĩ mô
Author: NGUYEN PHUC BINH
Author-email: nguyenphucbinh67@gmail.com
Keywords: stockvn,rpv,rstockvn,report stock vn,báo cáo tài chính việt nam,lấy báo cáo tài chính việt nam bằng python,lấy báo cáo tài chính về excel,lấy báo cáo tài chính về excel bằng python
Classifier: Programming Language :: Python :: 3
Classifier: License :: OSI Approved :: MIT License
Classifier: Operating System :: OS Independent
License-File: LICENSE
Requires-Dist: pandas
Requires-Dist: requests
Requires-Dist: jsonschema
Requires-Dist: bs4
Requires-Dist: selenium
Requires-Dist: undetected_chromedriver
Requires-Dist: webdriver_manager
Requires-Dist: html5lib
Requires-Dist: lxml
Requires-Dist: jsons
Requires-Dist: unidecode
Requires-Dist: urllib3
Requires-Dist: gdown
Requires-Dist: cryptography
Requires-Dist: chromedriver_autoinstaller
Requires-Dist: cython
Requires-Dist: openpyxl
Requires-Dist: setuptools
Requires-Dist: click
Dynamic: author
Dynamic: author-email
Dynamic: classifier
Dynamic: description
Dynamic: description-content-type
Dynamic: keywords
Dynamic: requires-dist
Dynamic: summary
